rios_preprocessor/__init__.py
rios_preprocessor/rios_preprocessor.py
rios_preprocessor-0.1.8.dist-info/DESCRIPTION.rst
rios_preprocessor-0.1.8.dist-info/METADATA
rios_preprocessor-0.1.8.dist-info/RECORD
rios_preprocessor-0.1.8.dist-info/WHEEL
rios_preprocessor-0.1.8.dist-info/metadata.json
rios_preprocessor-0.1.8.dist-info/top_level.txt
