Metadata-Version: 2.0
Name: rios-preprocessor
Version: 0.1.8
Summary: Preprocessor for the Natural Capital Project's RIOS software package
Home-page: http://github.com/leonbaruah/rios_preprocessor
Author: Leon Baruah
Author-email: leon.s.baruah@gmail.com
License: Modified BSD License
Keywords: RIOS
Platform: any
Classifier: Programming Language :: Python :: 2
Classifier: Programming Language :: Python :: 3
Classifier: Development Status :: 4 - Beta
Classifier: Natural Language :: English
Classifier: Intended Audience :: Developers
Classifier: Intended Audience :: Science/Research
Classifier: License :: OSI Approved :: BSD License
Classifier: Operating System :: OS Independent
Classifier: Topic :: Scientific/Engineering :: GIS
Requires-Dist: fiona (>=1.6.3)
Requires-Dist: geopandas (>=0.1.1)
Requires-Dist: numpy (>=1.10.1)
Requires-Dist: pandas (>=0.18.0)
Requires-Dist: pygeoprocessing (~=0.3.3)
Requires-Dist: rasterio (>=0.36.0)
Requires-Dist: shapely (>=1.5.13)
